telebaka_lprutils/bot.py
telebaka_lprutils/preferences.py
telebaka_lprutils-0.1.2.dist-info/METADATA
telebaka_lprutils-0.1.2.dist-info/RECORD
telebaka_lprutils-0.1.2.dist-info/WHEEL
telebaka_lprutils-0.1.2.dist-info/top_level.txt
